{
  "books": [
    {
      "text": "ggh",
      "day": "hh",
      "reminder": false,
      "id": "s6MxeP3"
    },
    {
      "text": "bh",
      "day": "hh",
      "reminder": true,
      "id": "TihrEyO"
    },
    {
      "text": "dns",
      "day": "mm",
      "reminder": true,
      "id": "LFZjg37"
    },
    {
      "text": "hhhh",
      "day": "shhh",
      "reminder": true,
      "id": "J76QahV"
    },
    {
      "text": "gff",
      "day": "11",
      "reminder": true,
      "id": "p4R4WH6"
    },
    {
      "text": "jj",
      "day": "hh",
      "reminder": true,
      "id": "PeUvhw1"
    },
    {
      "text": "gff",
      "day": "11",
      "reminder": true,
      "id": "YEnOSrU"
    },
    {
      "text": "bhbhh",
      "day": "gg",
      "reminder": true,
      "id": "9MHJggf"
    },
    {
      "text": "gff",
      "day": "11",
      "id": "M5W0FXz"
    },
    {
      "text": "gff",
      "day": "bb",
      "id": "s_48PkP"
    },
    {
      "text": "gff",
      "day": "ehheb",
      "id": "qY29MTB"
    },
    {
      "text": "nhh",
      "day": "hhh",
      "id": "SA8yDM8"
    },
    {
      "text": "njnn",
      "day": "",
      "id": "sOd9mzT"
    },
    {
      "text": "hhhh",
      "day": "jhhh",
      "id": "mA2jCgA"
    },
    {
      "text": "ggg",
      "day": "11",
      "id": "p_hEfdW"
    }
  ]
}